.gitignore
.travis.yml
HISTORY.md
MANIFEST.in
README.md
TODO.md
runpizza.py
setup.py
setup_long_description.rst
tox.ini
Pizza.egg-info/PKG-INFO
Pizza.egg-info/SOURCES.txt
Pizza.egg-info/dependency_links.txt
Pizza.egg-info/entry_points.txt
Pizza.egg-info/top_level.txt
docs/developing.md
docs/releasing.md
pizza/__init__.py
pizza/pizza.py
pizza/general/__init__.py
pizza/general/common.py
pizza/general/logconfig.py
pizza/general/optionparser.py
pizza/scripts/__init__.py
pizza/scripts/pizza/__init__.py
pizza/scripts/pizza/__main__.py
pizza/scripts/pizza/argparsing.py
pizza/scripts/pizza/main.py
pizza/test/__init__.py
pizza/test/harness/__init__.py
pizza/test/harness/main.py
pizza/test/harness/general/__init__.py
pizza/test/harness/general/loading.py
pizza/test/pizza/__init__.py
pizza/test/pizza/test_pizza.py
pizza/test/pizza/test_temp.py
pizza_setup/__init__.py
pizza_setup/utils.py
pizza_setup/test/__init__.py
pizza_setup/test/test_utils.py