Metadata-Version: 1.1
Name: Pizza
Version: 0.1.1
Summary: a model project for a Python command-line script
Home-page: https://github.com/cjerdonek/groome-python-expected
Author: Chris Jerdonek
Author-email: chris.jerdonek@gmail.com
License: UNKNOWN
Keywords: project template groome molt pystache mustache
Platform: UNKNOWN
Classifier: Development Status :: 2 - Pre-Alpha
Classifier: License :: OSI Approved :: BSD License
Classifier: Programming Language :: Python
Classifier: Programming Language :: Python :: 2
Classifier: Programming Language :: Python :: 2.7
Classifier: Programming Language :: Python :: 3
Classifier: Programming Language :: Python :: 3.2
Classifier: Programming Language :: Python :: 3.3
Classifier: Programming Language :: Python :: Implementation :: PyPy
